toystat/__init__.py
toystat/hello.py
toystat-0.0.1.dist-info/METADATA
toystat-0.0.1.dist-info/WHEEL
toystat-0.0.1.dist-info/licenses/LICENSE
toystat-0.0.1.dist-info/RECORD
