Metadata-Version: 2.1
Name: toystat
Version: 0.0.1
Summary: ToyStat
Author-email: Xiangzhuang Shen <datahonor@gmail.com>
License-File: LICENSE
Requires-Python: >=3.8
